Metadata-Version: 2.1
Name: idlweb
Version: 0.2
Summary: Sipmle Library in python for login web site
Author: issam iso
Classifier: Programming Language :: Python :: 3 
Classifier: Operating System :: OS Independent
Classifier: License :: OSI Approved :: MIT License
License-File: LICENSE.txt
